setup.py
bin/ismerged
bin/isreleased
trackmerge/__init__.py
trackmerge.egg-info/PKG-INFO
trackmerge.egg-info/SOURCES.txt
trackmerge.egg-info/dependency_links.txt
trackmerge.egg-info/not-zip-safe
trackmerge.egg-info/requires.txt
trackmerge.egg-info/top_level.txt