Metadata-Version: 1.0
Name: trackmerge
Version: 0.2.6
Summary: Tool for tracking project release versions with git.
Home-page: https://github.com/andrewguy9/trackmerge
Author: andrew thomson
Author-email: athomsonguy@gmail.com
License: UNKNOWN
Platform: UNKNOWN
